<?xml version="1.0" encoding="UTF-8" standalone="no"?><annotation>
	<folder>images</folder>
	<filename>20191126_160815.jpg</filename>
	<path>T22_AD_Detection/datasets/fstudent_dataset/cones/images/</path>
	<source>
		<database>Unknown</database>
	</source>
	<size>
		<width>4032</width>
		<height>3024</height>
		<depth>3</depth>
	</size>
	<segmented>0</segmented>
	<object>
		<name>blue</name>
		<pose>Unspecified</pose>
		<truncated>0</truncated>
		<difficult>0</difficult>
		<bndbox>
			<xmin>1385</xmin>
			<ymin>2067</ymin>
			<xmax>1754</xmax>
			<ymax>2506</ymax>
		</bndbox>
	</object>
	<object>
		<name>orange</name>
		<pose>Unspecified</pose>
		<truncated>0</truncated>
		<difficult>0</difficult>
		<bndbox>
			<xmin>2239</xmin>
			<ymin>1472</ymin>
			<xmax>2413</xmax>
			<ymax>1672</ymax>
		</bndbox>
	</object>
	<object>
		<name>yellow</name>
		<pose>Unspecified</pose>
		<truncated>0</truncated>
		<difficult>0</difficult>
		<bndbox>
			<xmin>3023</xmin>
			<ymin>1683</ymin>
			<xmax>3484</xmax>
			<ymax>2201</ymax>
		</bndbox>
	</object>
</annotation>